pyvueeel/__init__.py
pyvueeel/pyvueeel_internal.py
pyvueeel-0.0.6.dist-info/LICENSE
pyvueeel-0.0.6.dist-info/METADATA
pyvueeel-0.0.6.dist-info/WHEEL
pyvueeel-0.0.6.dist-info/top_level.txt
pyvueeel-0.0.6.dist-info/RECORD
